{"cameraMode":{"drawMode":0,"name":"Shaded","section":"Shading Mode"},"sceneLighting":true,"audioPlay":false,"sceneViewState":{"m_AlwaysRefresh":false,"showFog":true,"showSkybox":false,"showFlares":true,"showImageEffects":true,"showParticleSystems":true,"showVisualEffectGraphs":true,"m_FxEnabled":true},"in2DMode":false,"pivot":{"x":138.1999969482422,"y":14.0,"z":5.0},"rotation":{"x":0.18109333515167237,"y":-0.8094519376754761,"z":0.3261883556842804,"w":0.455610990524292},"size":65.77261352539063,"orthographic":false}